odoo/addons/web_responsive/README.rst
odoo/addons/web_responsive/__init__.py
odoo/addons/web_responsive/__manifest__.py
odoo/addons/web_responsive/i18n/ar.po
odoo/addons/web_responsive/i18n/ca.po
odoo/addons/web_responsive/i18n/da.po
odoo/addons/web_responsive/i18n/de.po
odoo/addons/web_responsive/i18n/es.po
odoo/addons/web_responsive/i18n/es_VE.po
odoo/addons/web_responsive/i18n/fr.po
odoo/addons/web_responsive/i18n/fr_BE.po
odoo/addons/web_responsive/i18n/fr_FR.po
odoo/addons/web_responsive/i18n/hr.po
odoo/addons/web_responsive/i18n/it.po
odoo/addons/web_responsive/i18n/nl.po
odoo/addons/web_responsive/i18n/pl.po
odoo/addons/web_responsive/i18n/pt.po
odoo/addons/web_responsive/i18n/pt_BR.po
odoo/addons/web_responsive/i18n/ru.po
odoo/addons/web_responsive/i18n/tr.po
odoo/addons/web_responsive/i18n/uk_UA.po
odoo/addons/web_responsive/i18n/web_responsive.pot
odoo/addons/web_responsive/i18n/zh_CN.po
odoo/addons/web_responsive/models/__init__.py
odoo/addons/web_responsive/models/ir_http.py
odoo/addons/web_responsive/models/res_users.py
odoo/addons/web_responsive/readme/CONTRIBUTORS.md
odoo/addons/web_responsive/readme/DESCRIPTION.md
odoo/addons/web_responsive/readme/ROADMAP.md
odoo/addons/web_responsive/readme/USAGE.md
odoo/addons/web_responsive/static/description/icon.png
odoo/addons/web_responsive/static/description/index.html
odoo/addons/web_responsive/static/img/appmenu.gif
odoo/addons/web_responsive/static/img/appsearch.gif
odoo/addons/web_responsive/static/img/breadcrumbs.gif
odoo/addons/web_responsive/static/img/calendar.gif
odoo/addons/web_responsive/static/img/chatter-colors.png
odoo/addons/web_responsive/static/img/chatter.png
odoo/addons/web_responsive/static/img/chatter_sided.gif
odoo/addons/web_responsive/static/img/chatter_topbar.gif
odoo/addons/web_responsive/static/img/default_icon_app.png
odoo/addons/web_responsive/static/img/device_rotation.gif
odoo/addons/web_responsive/static/img/document_viewer.gif
odoo_addon_web_responsive-19.0.1.0.1.dist-info/METADATA
odoo_addon_web_responsive-19.0.1.0.1.dist-info/WHEEL
odoo_addon_web_responsive-19.0.1.0.1.dist-info/top_level.txt
odoo_addon_web_responsive-19.0.1.0.1.dist-info/RECORD
