Metadata-Version: 2.1
Name: odoo-addon-web_responsive
Version: 19.0.1.0.1
Requires-Dist: odoo==19.0.*
Summary: Responsive web client, community-supported
Home-page: https://github.com/OCA/web
License: LGPL-3
Author: LasLabs, Tecnativa, ITerra, Onestein, Odoo Community Association (OCA)
Author-email: support@odoo-community.org
Classifier: Programming Language :: Python
Classifier: Framework :: Odoo
Classifier: Framework :: Odoo :: 19.0
Classifier: License :: OSI Approved :: GNU Lesser General Public License v3 (LGPLv3)
Classifier: Development Status :: 5 - Production/Stable
